cr_trichome-0.1.1.dist-info/METADATA
cr_trichome-0.1.1.dist-info/WHEEL
cr_trichome-0.1.1.dist-info/licenses/LICENSE
cr_trichome/plotting.py
cr_trichome/simulation.py
cr_trichome/analysis.py
cr_trichome/py.typed
cr_trichome/__init__.py
cr_trichome/storage.py
cr_trichome/_cr_trichome_rust.cpython-310-powerpc64le-linux-gnu.so
cr_trichome-0.1.1.dist-info/RECORD
