Metadata-Version: 2.4
Name: cr_trichome
Version: 0.1.1
Classifier: Programming Language :: Rust
Classifier: Programming Language :: Python :: Implementation :: CPython
Classifier: Programming Language :: Python :: Implementation :: PyPy
License-File: LICENSE
Requires-Python: >=3.8
